{
	"@type":"NativeView",
	"Name":"Default",
	"Columns":
	[
		{
			"Subset":
			{
				"@id":"Dimensions('Period')/Hierarchies('Period')/Subsets('Default')"
			}
		}
	],
	"Rows":
	[
		{
			"Subset":
			{
				"Hierarchy":
				{
					"@id":"Dimensions('Region')/Hierarchies('Region')"
				},
				"Elements":
				[
					{
						"@id":"Dimensions('Region')/Hierarchies('Region')/Elements('13')"
					},
					{
						"@id":"Dimensions('Region')/Hierarchies('Region')/Elements('3')"
					},
					{
						"@id":"Dimensions('Region')/Hierarchies('Region')/Elements('4')"
					},
					{
						"@id":"Dimensions('Region')/Hierarchies('Region')/Elements('5')"
					},
					{
						"@id":"Dimensions('Region')/Hierarchies('Region')/Elements('6')"
					},
					{
						"@id":"Dimensions('Region')/Hierarchies('Region')/Elements('7')"
					},
					{
						"@id":"Dimensions('Region')/Hierarchies('Region')/Elements('8')"
					},
					{
						"@id":"Dimensions('Region')/Hierarchies('Region')/Elements('11')"
					},
					{
						"@id":"Dimensions('Region')/Hierarchies('Region')/Elements('12')"
					}
				]
			}
		}
	],
	"Titles":
	[
		{
			"Subset":
			{
				"Hierarchy":
				{
					"@id":"Dimensions('Version')/Hierarchies('Version')"
				},
				"Expression":"TM1SubsetAll([Version])"
			},
			"Selected":
			{
				"@id":"Dimensions('Version')/Hierarchies('Version')/Elements('Actual vs Budget %')"
			}
		},
		{
			"Subset":
			{
				"Hierarchy":
				{
					"@id":"Dimensions('Year')/Hierarchies('Year')"
				},
				"Expression":"TM1SubsetAll([Year])"
			},
			"Selected":
			{
				"@id":"Dimensions('Year')/Hierarchies('Year')/Elements('2013')"
			}
		},
		{
			"Subset":
			{
				"Hierarchy":
				{
					"@id":"Dimensions('Regional Assumptions Measure')/Hierarchies('Regional Assumptions Measure')"
				},
				"Elements":
				[
					{
						"@id":"Dimensions('Regional Assumptions Measure')/Hierarchies('Regional Assumptions Measure')/Elements('Company Tax Rate')"
					},
					{
						"@id":"Dimensions('Regional Assumptions Measure')/Hierarchies('Regional Assumptions Measure')/Elements('Super Rate')"
					},
					{
						"@id":"Dimensions('Regional Assumptions Measure')/Hierarchies('Regional Assumptions Measure')/Elements('Payroll Tax Rate')"
					},
					{
						"@id":"Dimensions('Regional Assumptions Measure')/Hierarchies('Regional Assumptions Measure')/Elements('Annual Leave Rate')"
					},
					{
						"@id":"Dimensions('Regional Assumptions Measure')/Hierarchies('Regional Assumptions Measure')/Elements('Worker Compensation Rate')"
					}
				]
			},
			"Selected":
			{
				"@id":"Dimensions('Regional Assumptions Measure')/Hierarchies('Regional Assumptions Measure')/Elements('Worker Compensation Rate')"
			}
		}
	],
	"SuppressEmptyColumns":false,
	"SuppressEmptyRows":false,
	"FormatString":"0.#########"
}