{
	"@type":"Subset",
	"Name":"Default",
	"Elements":
	[
		{
			"@id":"Dimensions('m_location')/Hierarchies('m_location')/Elements('All Locations')"
		},
		{
			"@id":"Dimensions('m_location')/Hierarchies('m_location')/Elements('AU')"
		},
		{
			"@id":"Dimensions('m_location')/Hierarchies('m_location')/Elements('NSW')"
		},
		{
			"@id":"Dimensions('m_location')/Hierarchies('m_location')/Elements('Sydney')"
		},
		{
			"@id":"Dimensions('m_location')/Hierarchies('m_location')/Elements('VIC')"
		},
		{
			"@id":"Dimensions('m_location')/Hierarchies('m_location')/Elements('Melbourne')"
		},
		{
			"@id":"Dimensions('m_location')/Hierarchies('m_location')/Elements('QLD')"
		},
		{
			"@id":"Dimensions('m_location')/Hierarchies('m_location')/Elements('Brisbane')"
		},
		{
			"@id":"Dimensions('m_location')/Hierarchies('m_location')/Elements('SA')"
		},
		{
			"@id":"Dimensions('m_location')/Hierarchies('m_location')/Elements('Adelaide')"
		},
		{
			"@id":"Dimensions('m_location')/Hierarchies('m_location')/Elements('WA')"
		},
		{
			"@id":"Dimensions('m_location')/Hierarchies('m_location')/Elements('Perth')"
		},
		{
			"@id":"Dimensions('m_location')/Hierarchies('m_location')/Elements('NZ')"
		},
		{
			"@id":"Dimensions('m_location')/Hierarchies('m_location')/Elements('NI')"
		},
		{
			"@id":"Dimensions('m_location')/Hierarchies('m_location')/Elements('Auckland')"
		},
		{
			"@id":"Dimensions('m_location')/Hierarchies('m_location')/Elements('SI')"
		},
		{
			"@id":"Dimensions('m_location')/Hierarchies('m_location')/Elements('Christchurch')"
		}
	]
}