{
	"@type":"Process",
	"Name":"Bedrock.Dim.ExportToFile",
	"HasSecurityAccess":true,
	"Code@Code.link":"Bedrock.Dim.ExportToFile.ti",
	"UIData":"CubeAction=1511€DataAction=1503€CubeLogChanges=0€",
	"VariablesUIData":
	[
		"VarType=32€ColType=827€"
	],
	"DataSource":
	{
		"Type":"TM1DimensionSubset",
		"dataSourceNameForClient":"}Cubes",
		"dataSourceNameForServer":"}Cubes",
		"subset":"All"
	},
	"Parameters":
	[
		{
			"Name":"pDimension",
			"Prompt":"Dimension",
			"Value":"",
			"Type":"String"
		},
		{
			"Name":"pExportPath",
			"Prompt":"Export file path",
			"Value":"",
			"Type":"String"
		},
		{
			"Name":"pExportFile",
			"Prompt":"Export file name (default extension .csv)",
			"Value":"",
			"Type":"String"
		},
		{
			"Name":"pTitleRecord",
			"Prompt":"Boolean 1 = Yes - Include header row",
			"Value":1,
			"Type":"Numeric"
		},
		{
			"Name":"pDebug",
			"Prompt":"Debug Mode",
			"Value":0,
			"Type":"Numeric"
		}
	],
	"Variables":
	[
		{
			"Name":"vElement",
			"Type":"String",
			"Position":1,
			"StartByte":0,
			"EndByte":0
		}
	]
}