{
	"@type":"Process",
	"Name":"Cub Sales Quota",
	"HasSecurityAccess":false,
	"Code@Code.link":"Cub Sales Quota.ti",
	"UIData":"CubeAction=1511€DataAction=1503€CubeLogChanges=0€",
	"VariablesUIData":
	[
		"VarType=32€ColType=827€",
		"VarType=32€ColType=827€",
		"VarType=32€ColType=827€",
		"VarType=32€ColType=827€",
		"VarType=32€ColType=827€",
		"VarType=33€ColType=827€"
	],
	"DataSource":
	{
		"Type":"ODBC",
		"dataSourceNameForClient":"AdventureWorks",
		"dataSourceNameForServer":"AdventureWorks",
		"password":"yCe43sI>1@[wu;hfMijlnv_fDa]h=Um8L2:hLvkM>[t\\R6kFa4d1;P=?na2mT=<9?4kFbThX6a<mo><Ml7KeG95aSa6HZu>r1v5DuCF_Y7JjB]jS=Np14T2F>VDiGvlYMfpAK?DY1B<XE]=Ktl5Y1u\\_NFm5XKzde\\8iK\\;a;=XQh:emlyc8EdaMZvyplp5dNS43dT>`",
		"query":"select * from FactSalesQuota",
		"userName":"",
		"usesUnicode":true
	},
	"Parameters":[],
	"Variables":
	[
		{
			"Name":"SalesQuotaKey",
			"Type":"String",
			"Position":1,
			"StartByte":0,
			"EndByte":0
		},
		{
			"Name":"EmployeeKey",
			"Type":"String",
			"Position":2,
			"StartByte":0,
			"EndByte":0
		},
		{
			"Name":"DateKey",
			"Type":"String",
			"Position":3,
			"StartByte":0,
			"EndByte":0
		},
		{
			"Name":"CalendarYear",
			"Type":"String",
			"Position":4,
			"StartByte":0,
			"EndByte":0
		},
		{
			"Name":"CalendarQuarter",
			"Type":"String",
			"Position":5,
			"StartByte":0,
			"EndByte":0
		},
		{
			"Name":"SalesAmountQuota",
			"Type":"Numeric",
			"Position":6,
			"StartByte":0,
			"EndByte":0
		}
	]
}